querycontacts/__init__.py
querycontacts/_version.py
querycontacts-2.0.0.data/scripts/querycontacts
querycontacts-2.0.0.dist-info/LICENSE
querycontacts-2.0.0.dist-info/METADATA
querycontacts-2.0.0.dist-info/WHEEL
querycontacts-2.0.0.dist-info/top_level.txt
querycontacts-2.0.0.dist-info/RECORD
