Metadata-Version: 2.1
Name: querycontacts
Version: 2.0.0
Summary: Query network abuse contacts on the command-line for a given ip address on abuse-contacts.abusix.zone
Home-page: https://github.com/abusix/querycontacts
Author: abusix
Author-email: fp@abusix.com
License: GNU General Public License v3 (GPLv3)
Project-URL: Source, https://github.com/abusix/querycontacts
Project-URL: Company, https://www.abusix.com/
Keywords: contact,query,dns,abuse contact,abuse,abusix,network
Platform: UNKNOWN
Classifier: Development Status :: 5 - Production/Stable
Classifier: Intended Audience :: Customer Service
Classifier: Intended Audience :: System Administrators
Classifier: Intended Audience :: Developers
Classifier: License :: OSI Approved :: GNU General Public License v3 (GPLv3)
Classifier: Programming Language :: Python :: 3
Classifier: Programming Language :: Python :: 3.6
Classifier: Programming Language :: Python :: 3.7
Classifier: Programming Language :: Python :: 3.8
Classifier: Programming Language :: Python :: 3.9
Classifier: Topic :: Security
Requires-Python: >=3
Requires-Dist: dnspython (<3,>=2)
